tencentApi/__init__.py
tencentApi/api.py
tencentApi/cli/__init__.py
tencentApi/cli/app.py
tencentApi/cns/__init__.py
tencentApi/cns/cns.py
tencentApi/cns/ddns.py
tencentApi-0.1.0.dist-info/LICENSE
tencentApi-0.1.0.dist-info/METADATA
tencentApi-0.1.0.dist-info/WHEEL
tencentApi-0.1.0.dist-info/entry_points.txt
tencentApi-0.1.0.dist-info/top_level.txt
tencentApi-0.1.0.dist-info/RECORD
