Metadata-Version: 2.1
Name: tencentApi
Version: 0.1.0
Summary: 腾讯云资源api，补充cns模块的api函数，实现动态域名解析。
Home-page: https://github.com/shenchucheng/tencentapi
Author: shenchucheng
Author-email: shenchucheng@126.com
License: UNKNOWN
Platform: UNKNOWN
Classifier: Programming Language :: Python :: 3
Classifier: License :: OSI Approved :: MIT License
Classifier: Operating System :: OS Independent
Requires-Python: >=3.6
Requires-Dist: fire (>=0.3.1)
Requires-Dist: requests (>=2.23.0)
